dvmncards/__init__.py
dvmncards/anki_deck.py
dvmncards/anki/__init__.py
dvmncards/anki/collection.py
dvmncards/anki/consts.py
dvmncards/anki/decks.py
dvmncards/anki/exporting.py
dvmncards/anki/media.py
dvmncards/anki/notes.py
dvmncards-0.0.2.dist-info/LICENSE
dvmncards-0.0.2.dist-info/METADATA
dvmncards-0.0.2.dist-info/WHEEL
dvmncards-0.0.2.dist-info/top_level.txt
dvmncards-0.0.2.dist-info/RECORD
