Metadata-Version: 2.1
Name: dvmncards
Version: 0.0.2
Summary: Create anki cards and export its in .apkg
Home-page: https://github.com/djeck1432/anki_deck
Author: Djeck
Author-email: work7kost@gmail.com
License: UNKNOWN
Platform: UNKNOWN
Classifier: Programming Language :: Python :: 3
Classifier: License :: OSI Approved :: MIT License
Classifier: Operating System :: OS Independent
Requires-Python: >=3.6
